{
  "data": [
    {
      "type": "bar",
      "x": [
        "r3836",
        "r3843"
      ],
      "y": [
        88,
        36
      ],
      "name": "Crash-free",
      "text": [
        "97%",
        "92%"
      ],
      "textposition": "inside",
      "insidetextanchor": "middle",
      "hovertext": [
        "r3836 (g8f7c553)<br>88 crash-free / 91 sessions (96.7%)",
        "r3843 (gfe8df22)<br>36 crash-free / 39 sessions (92.3%)"
      ],
      "hoverinfo": "text",
      "marker": {
        "color": "#8ec1a8"
      }
    },
    {
      "type": "bar",
      "x": [
        "r3836",
        "r3843"
      ],
      "y": [
        3,
        3
      ],
      "name": "Crashed",
      "hovertext": [
        "r3836 (g8f7c553)<br>3 crashed sessions",
        "r3843 (gfe8df22)<br>3 crashed sessions"
      ],
      "hoverinfo": "text",
      "marker": {
        "color": "#e8a598"
      }
    },
    {
      "type": "scatter",
      "mode": "lines+markers",
      "x": [
        "r3836",
        "r3843"
      ],
      "y": [
        42.911,
        9.844
      ],
      "yaxis": "y2",
      "name": "MTBF (uptime before crash)",
      "hovertext": [
        "r3836 (g8f7c553)<br>MTBF 43 min<br>(mean uptime before crash, n=3)",
        "r3843 (gfe8df22)<br>MTBF 10 min<br>(mean uptime before crash, n=3)"
      ],
      "hoverinfo": "text",
      "connectgaps": false,
      "marker": {
        "color": "#222222",
        "size": 9,
        "line": {
          "color": "#ffffff",
          "width": 1
        }
      },
      "line": {
        "color": "#222222",
        "width": 3
      }
    }
  ],
  "layout": {
    "title": {
      "text": "Sessions per release \u2014 global 94.9% crash-free \u00b7 avg session 67 min over 217 sessions (the last 2 days)"
    },
    "barmode": "stack",
    "xaxis": {
      "title": {
        "text": "Release"
      },
      "type": "category"
    },
    "yaxis": {
      "title": {
        "text": "Sessions"
      },
      "rangemode": "tozero"
    },
    "legend": {
      "orientation": "h",
      "x": 0,
      "y": 1.1
    },
    "margin": {
      "t": 80,
      "r": 70,
      "b": 60,
      "l": 60
    },
    "showlegend": true,
    "yaxis2": {
      "title": {
        "text": "MTBF: mean uptime before crash (min)"
      },
      "overlaying": "y",
      "side": "right",
      "rangemode": "tozero",
      "ticksuffix": " min",
      "showgrid": false
    }
  }
}