{
  "data": [
    {
      "type": "bar",
      "x": [
        "NVIDIA RTX A400",
        "Apple M2 Pro",
        "Intel UHD Graphics 630",
        "Apple M5",
        "Apple M1",
        "gfx1032",
        "Apple M4 Pro",
        "NVIDIA GeForce RTX 4060 Laptop GPU",
        "NVIDIA GeForce RTX 3050",
        "NVIDIA GeForce RTX 2070 SUPER",
        "NVIDIA GeForce RTX 3060 Ti",
        "NVIDIA GeForce GTX 1060 6GB",
        "Intel UHD Graphics",
        "Apple M2",
        "NVIDIA GeForce GTX 1650 with Max-Q Design",
        "NVIDIA GeForce GTX 1050 Ti",
        "AMD Radeon R9 M390X",
        "Apple M1 Pro",
        "NVIDIA GeForce RTX 3060",
        "Quadro M2200"
      ],
      "y": [
        10,
        6,
        5,
        3,
        3,
        3,
        3,
        2,
        2,
        2,
        2,
        2,
        2,
        2,
        2,
        2,
        2,
        2,
        2,
        2
      ],
      "hovertext": [
        "NVIDIA RTX A400<br>10 users",
        "Apple M2 Pro<br>6 users",
        "Intel UHD Graphics 630<br>5 users",
        "Apple M5<br>3 users",
        "Apple M1<br>3 users",
        "gfx1032<br>3 users",
        "Apple M4 Pro<br>3 users",
        "NVIDIA GeForce RTX 4060 Laptop GPU<br>2 users",
        "NVIDIA GeForce RTX 3050<br>2 users",
        "NVIDIA GeForce RTX 2070 SUPER<br>2 users",
        "NVIDIA GeForce RTX 3060 Ti<br>2 users",
        "NVIDIA GeForce GTX 1060 6GB<br>2 users",
        "Intel UHD Graphics<br>2 users",
        "Apple M2<br>2 users",
        "NVIDIA GeForce GTX 1650 with Max-Q Design<br>2 users",
        "NVIDIA GeForce GTX 1050 Ti<br>2 users",
        "AMD Radeon R9 M390X<br>2 users",
        "Apple M1 Pro<br>2 users",
        "NVIDIA GeForce RTX 3060<br>2 users",
        "Quadro M2200<br>2 users"
      ],
      "hoverinfo": "text",
      "marker": {
        "color": "#9db4d0"
      }
    }
  ],
  "layout": {
    "title": {
      "text": "Graphics cards in use \u2014 59 users"
    },
    "xaxis": {
      "type": "category",
      "tickangle": -40,
      "automargin": true
    },
    "yaxis": {
      "title": {
        "text": "Users"
      },
      "rangemode": "tozero"
    },
    "margin": {
      "t": 70,
      "r": 30,
      "b": 120,
      "l": 60
    },
    "showlegend": false
  }
}